Metadata-Version: 1.1
Name: service-registry-cli
Version: 0.2.1
Summary: Command line client for Rackspace Service Registry
Home-page: https://github.com/racker/python-service-registry-cli
Author: Rackspace Hosting
Author-email: sr@rackspace.com
License: UNKNOWN
Platform: Any
Classifier: Development Status :: 4 - Beta
Classifier: License :: OSI Approved :: Apache Software License
Classifier: Programming Language :: Python
Classifier: Programming Language :: Python :: 2.6
Classifier: Programming Language :: Python :: 2.7
Classifier: Programming Language :: Python :: Implementation :: PyPy
Classifier: Environment :: Console
